rotating_proxies/__init__.py
rotating_proxies/expire.py
rotating_proxies/middlewares.py
rotating_proxies/policy.py
rotating_proxies/utils.py
scrapy_rotating_proxies-0.6.2.dist-info/DESCRIPTION.rst
scrapy_rotating_proxies-0.6.2.dist-info/METADATA
scrapy_rotating_proxies-0.6.2.dist-info/RECORD
scrapy_rotating_proxies-0.6.2.dist-info/WHEEL
scrapy_rotating_proxies-0.6.2.dist-info/metadata.json
scrapy_rotating_proxies-0.6.2.dist-info/top_level.txt
