Metadata-Version: 1.1
Name: scrapy-rotating-proxies
Version: 0.6.2
Summary: Rotating proxies for Scrapy
Home-page: https://github.com/TeamHG-Memex/scrapy-rotating-proxies
Author: Mikhail Korobov
Author-email: kmike84@gmail.com
License: MIT license
Platform: UNKNOWN
Classifier: Development Status :: 3 - Alpha
Classifier: License :: OSI Approved :: MIT License
Classifier: Intended Audience :: Developers
Classifier: Operating System :: OS Independent
Classifier: Framework :: Scrapy
Classifier: Programming Language :: Python
Classifier: Programming Language :: Python :: 2
Classifier: Programming Language :: Python :: 2.7
Classifier: Programming Language :: Python :: 3
Classifier: Programming Language :: Python :: 3.4
Classifier: Programming Language :: Python :: 3.5
Classifier: Programming Language :: Python :: 3.6
